pyzim/__init__.py
pyzim/archive.py
pyzim/bindable.py
pyzim/blob.py
pyzim/cache.py
pyzim/cluster.py
pyzim/compression.py
pyzim/compressionstrategy.py
pyzim/constants.py
pyzim/counter.py
pyzim/entry.py
pyzim/exceptions.py
pyzim/header.py
pyzim/item.py
pyzim/mimetypelist.py
pyzim/modifiable.py
pyzim/operationbuffer.py
pyzim/pointerlist.py
pyzim/policy.py
pyzim/processor.py
pyzim/search.py
pyzim/spaceallocator.py
pyzim/util/__init__.py
pyzim/util/ioutil.py
pyzim/util/iter.py
pyzim/util/translator.py
python_zim-0.1.2.dist-info/METADATA
python_zim-0.1.2.dist-info/WHEEL
python_zim-0.1.2.dist-info/licenses/LICENSE
python_zim-0.1.2.dist-info/RECORD
