Metadata-Version: 2.4
Name: python-zim
Version: 0.1.2
Summary: Library for working with ZIM files
Project-URL: Homepage, https://github.com/imaybeabitshy/pyzim
Project-URL: Bug Tracker, https://github.com/imaybeabitshy/pyzim/issues
Author-email: IMayBeABitShy <imaybeabitshy@gmail.com>
License: MIT License
License-File: LICENSE
Classifier: License :: OSI Approved :: MIT License
Classifier: Operating System :: OS Independent
Classifier: Programming Language :: Python :: 3
Classifier: Topic :: File Formats
Requires-Python: >=3.7
Provides-Extra: all
Requires-Dist: pyzstd; extra == 'all'
Requires-Dist: rigour; extra == 'all'
Requires-Dist: tox; extra == 'all'
Requires-Dist: xapian-bindings; extra == 'all'
Requires-Dist: zstandard; extra == 'all'
Provides-Extra: compression
Requires-Dist: zstandard; extra == 'compression'
Provides-Extra: search
Requires-Dist: rigour; extra == 'search'
Requires-Dist: xapian-bindings; extra == 'search'
Provides-Extra: testing
Requires-Dist: pyzstd; extra == 'testing'
Requires-Dist: tox; extra == 'testing'
